ndv/__init__.py
ndv/_types.py
ndv/data.py
ndv/py.typed
ndv/util.py
ndv/controllers/__init__.py
ndv/controllers/_array_viewer.py
ndv/controllers/_channel_controller.py
ndv/models/__init__.py
ndv/models/_array_display_model.py
ndv/models/_base_model.py
ndv/models/_data_display_model.py
ndv/models/_data_wrapper.py
ndv/models/_lut_model.py
ndv/models/_mapping.py
ndv/models/_reducer.py
ndv/models/_ring_buffer.py
ndv/models/_roi_model.py
ndv/models/_viewer_model.py
ndv/views/__init__.py
ndv/views/_app.py
ndv/views/_jupyter/__init__.py
ndv/views/_jupyter/_app.py
ndv/views/_jupyter/_array_view.py
ndv/views/_pygfx/__init__.py
ndv/views/_pygfx/_array_canvas.py
ndv/views/_pygfx/_histogram.py
ndv/views/_pygfx/_util.py
ndv/views/_qt/__init__.py
ndv/views/_qt/_app.py
ndv/views/_qt/_array_view.py
ndv/views/_qt/_main_thread.py
ndv/views/_qt/_save_button.py
ndv/views/_resources/spin.gif
ndv/views/_vispy/__init__.py
ndv/views/_vispy/_array_canvas.py
ndv/views/_vispy/_histogram.py
ndv/views/_vispy/_plot_widget.py
ndv/views/_wx/__init__.py
ndv/views/_wx/_app.py
ndv/views/_wx/_array_view.py
ndv/views/_wx/_labeled_slider.py
ndv/views/_wx/_main_thread.py
ndv/views/_wx/range_slider.py
ndv/views/bases/__init__.py
ndv/views/bases/_app.py
ndv/views/bases/_array_view.py
ndv/views/bases/_lut_view.py
ndv/views/bases/_view_base.py
ndv/views/bases/_graphics/__init__.py
ndv/views/bases/_graphics/_canvas.py
ndv/views/bases/_graphics/_canvas_elements.py
ndv/views/bases/_graphics/_mouseable.py
ndv-0.4.0.dist-info/METADATA
ndv-0.4.0.dist-info/WHEEL
ndv-0.4.0.dist-info/licenses/LICENSE
ndv-0.4.0.dist-info/RECORD
