Metadata-Version: 2.4
Name: ndv
Version: 0.4.0
Summary: Simple, fast-loading, n-dimensional array viewer, with minimal dependencies.
Project-URL: homepage, https://github.com/pyapp-kit/ndv
Project-URL: repository, https://github.com/pyapp-kit/ndv
Author-email: Talley Lambert <talley.lambert@gmail.com>, Gabriel Selzer <gjselzer@wisc.edu>
License: BSD-3-Clause
License-File: LICENSE
Classifier: Development Status :: 3 - Alpha
Classifier: License :: OSI Approved :: BSD License
Classifier: Programming Language :: Python :: 3
Classifier: Programming Language :: Python :: 3.9
Classifier: Programming Language :: Python :: 3.10
Classifier: Programming Language :: Python :: 3.11
Classifier: Programming Language :: Python :: 3.12
Classifier: Programming Language :: Python :: 3.13
Classifier: Typing :: Typed
Requires-Python: >=3.9
Requires-Dist: cmap>=0.3
Requires-Dist: numpy>=1.23
Requires-Dist: psygnal>=0.10
Requires-Dist: pydantic>=2.9
Requires-Dist: typing-extensions>=4.0
Provides-Extra: jup
Requires-Dist: glfw>=2.4; extra == 'jup'
Requires-Dist: imageio[tifffile]>=2.20; extra == 'jup'
Requires-Dist: ipywidgets>=8.0.5; extra == 'jup'
Requires-Dist: jupyter-rfb>=0.3.3; extra == 'jup'
Requires-Dist: jupyter>=1.1; extra == 'jup'
Requires-Dist: pygfx>=0.8.0; extra == 'jup'
Provides-Extra: jupyter
Requires-Dist: glfw>=2.4; extra == 'jupyter'
Requires-Dist: ipywidgets>=8.0.5; extra == 'jupyter'
Requires-Dist: jupyter-rfb>=0.3.3; extra == 'jupyter'
Requires-Dist: jupyter>=1.1; extra == 'jupyter'
Provides-Extra: pygfx
Requires-Dist: pygfx>=0.8.0; extra == 'pygfx'
Provides-Extra: pyqt
Requires-Dist: pyqt6!=6.6,>=6.4; extra == 'pyqt'
Requires-Dist: pyqt6>=6.5.3; (python_version >= '3.12') and extra == 'pyqt'
Requires-Dist: qtpy>=2; extra == 'pyqt'
Requires-Dist: superqt[iconify]>=0.7.2; extra == 'pyqt'
Provides-Extra: pyside
Requires-Dist: numpy<2,>=1.23; (sys_platform == 'win32') and extra == 'pyside'
Requires-Dist: pyside6==6.6.3; (sys_platform == 'win32') and extra == 'pyside'
Requires-Dist: pyside6>=6.4; extra == 'pyside'
Requires-Dist: pyside6>=6.6; (python_version >= '3.12') and extra == 'pyside'
Requires-Dist: qtpy>=2; extra == 'pyside'
Requires-Dist: superqt[iconify,pyside6]>=0.7.2; extra == 'pyside'
Provides-Extra: qt
Requires-Dist: imageio[tifffile]>=2.20; extra == 'qt'
Requires-Dist: pygfx>=0.8.0; extra == 'qt'
Requires-Dist: pyqt6!=6.6,>=6.4; extra == 'qt'
Requires-Dist: pyqt6>=6.5.3; (python_version >= '3.12') and extra == 'qt'
Requires-Dist: qtpy>=2; extra == 'qt'
Requires-Dist: superqt[iconify]>=0.7.2; extra == 'qt'
Provides-Extra: vispy
Requires-Dist: pyopengl>=3.1; extra == 'vispy'
Requires-Dist: vispy>=0.14.3; extra == 'vispy'
Provides-Extra: wx
Requires-Dist: imageio[tifffile]>=2.20; extra == 'wx'
Requires-Dist: pyconify>=0.2.1; extra == 'wx'
Requires-Dist: pygfx>=0.8.0; extra == 'wx'
Requires-Dist: wxpython>=4.2.2; extra == 'wx'
Provides-Extra: wxpython
Requires-Dist: pyconify>=0.2.1; extra == 'wxpython'
Requires-Dist: wxpython>=4.2.2; extra == 'wxpython'
